bdms/__init__.py
bdms/mutators.py
bdms/poisson.py
bdms/tree.py
bdms/utils.py
bdms_sim-0.6.2.dist-info/METADATA
bdms_sim-0.6.2.dist-info/WHEEL
bdms_sim-0.6.2.dist-info/licenses/LICENSE
bdms_sim-0.6.2.dist-info/RECORD
