Metadata-Version: 2.4
Name: bdms-sim
Version: 0.6.2
Summary: Tree simulator for birth-death-mutation-sampling (BDMS) processes
Project-URL: Homepage, https://github.com/dewitt-lab/BDMS
Project-URL: Bug Tracker, https://github.com/dewitt-lab/BDMS/issues
Project-URL: Documentation, https://dewitt-lab.github.io/BDMS
Author-email: William DeWitt <wsdewitt@uw.edu>, Michael Celentano <mcelentano@berkeley.edu>, Thanasi Bakis <abakis@uci.edu>, Duncan Ralph <dkralph@gmail.com>, Sebastian Prillo <sprillo@berkeley.edu>, Frederick Matsen <ematsen@gmail.com>, Yun Song <yss@berkeley.edu>, Volodymyr Minin <yss@berkeley.edu>
License-File: LICENSE
Classifier: License :: OSI Approved :: MIT License
Classifier: Operating System :: OS Independent
Classifier: Programming Language :: Python :: 3
Requires-Python: >=3.11
Requires-Dist: ete3
Requires-Dist: matplotlib
Requires-Dist: numpy
Requires-Dist: pyqt5
Requires-Dist: scipy
